{
    "Pre_static_analysis": {
        "Filename": "BW/8c2cee6a57b93201ce76e760a795e10ce3850cb1cdee19ea51c5cc9efa56d871.apk", 
        "md5": "6bb83f167d1369b525f60b73d5162083", 
        "sha256": "8c2cee6a57b93201ce76e760a795e10ce3850cb1cdee19ea51c5cc9efa56d871", 
        "sha1": "31d815fc760f5b5db9c3bde7cb0df1638d7ea7bf", 
        "VT_positives": 0, 
        "VT_engines": 66, 
        "avclass": "None"
    }, 
    "Static_analysis": {
        "Package name": "com.touringplans.lines.android", 
        "Permissions": [
            "android.permission.INTERNET", 
            "android.permission.READ_PHONE_STATE", 
            "com.android.vending.BILLING"
        ], 
        "Opcodes": {
            "aget-byte": 46, 
            "invoke-static/range": 2, 
            "const-class": 1, 
            "move-object": 36, 
            "move-result-wide": 3, 
            "array-length": 13, 
            "sparse-switch-payload": 1, 
            "check-cast": 48, 
            "move": 21, 
            "if-eqz": 101, 
            "fill-array-data-payload": 4, 
            "and-int/lit8": 13, 
            "sub-int": 2, 
            "packed-switch": 1, 
            "invoke-static": 152, 
            "aput-object": 4, 
            "goto/16": 24, 
            "invoke-interface/range": 1, 
            "const/4": 193, 
            "mul-int/lit8": 2, 
            "sput-object": 8, 
            "instance-of": 5, 
            "int-to-byte": 8, 
            "sparse-switch": 1, 
            "shr-int/lit8": 2, 
            "if-ne": 17, 
            "const": 21, 
            "move-exception": 26, 
            "if-le": 4, 
            "packed-switch-payload": 1, 
            "sput-boolean": 1, 
            "sget-boolean": 1, 
            "div-int": 1, 
            "or-int": 5, 
            "iget-boolean": 8, 
            "add-int/lit8": 55, 
            "invoke-super": 8, 
            "move/from16": 6, 
            "div-int/lit8": 2, 
            "invoke-virtual": 790, 
            "iput-boolean": 13, 
            "move-result-object": 574, 
            "return-void": 96, 
            "invoke-virtual/range": 7, 
            "const/16": 39, 
            "invoke-interface": 87, 
            "iget": 7, 
            "return": 25, 
            "goto": 83, 
            "add-int/2addr": 5, 
            "return-wide": 1, 
            "if-lez": 2, 
            "if-lt": 4, 
            "iput": 5, 
            "const-string": 335, 
            "new-instance": 179, 
            "iput-object": 74, 
            "rsub-int": 1, 
            "if-nez": 33, 
            "iput-wide": 1, 
            "if-eq": 16, 
            "invoke-direct": 219, 
            "move-result": 111, 
            "long-to-int": 2, 
            "nop": 1, 
            "throw": 29, 
            "new-array": 11, 
            "const/high16": 2, 
            "invoke-direct/range": 2, 
            "iget-wide": 1, 
            "sget-object": 32, 
            "if-gt": 3, 
            "shl-int/lit8": 15, 
            "iget-object": 241, 
            "int-to-char": 2, 
            "aget-object": 7, 
            "fill-array-data": 4, 
            "move-object/from16": 46, 
            "add-int": 5, 
            "return-object": 54, 
            "or-int/2addr": 5, 
            "if-ge": 9, 
            "if-ltz": 4, 
            "aput-byte": 26, 
            "ushr-int/lit8": 30
        }, 
        "Main activity": "com.touringplans.lines.android.WDWLines", 
        "API calls": {
            "android.app.PendingIntent": 1, 
            "android.webkit.WebView.setScrollBarStyle": 1, 
            "android.app.Activity": 8, 
            "java.util.Locale": 3, 
            "android.content.Intent": 5, 
            "android.widget.LinearLayout": 5, 
            "android.content.Context": 12, 
            "android.webkit.JsResult": 1, 
            "android.util.Log.e": 10, 
            "android.util.Log.d": 29, 
            "android.webkit.WebView.goBack": 1, 
            "java.lang.CharSequence": 1, 
            "android.util.Log.i": 1, 
            "android.webkit.WebView": 19, 
            "java.lang.Object": 4, 
            "org.json.JSONException": 1, 
            "android.os.Parcel.obtain": 10, 
            "android.os.Handler": 3, 
            "java.lang.String.length": 2, 
            "java.lang.String.trim": 1, 
            "java.security.MessageDigest": 3, 
            "android.text.TextUtils": 3, 
            "android.webkit.WebView.setWebViewClient": 1, 
            "android.webkit.WebSettings.setSupportZoom": 1, 
            "android.app.Activity.onCreate": 1, 
            "android.os.Bundle.putStringArrayList": 1, 
            "java.net.URISyntaxException": 1, 
            "android.webkit.WebView.setLayoutParams": 2, 
            "android.os.Parcel.writeNoException": 5, 
            "java.lang.String.toLowerCase": 2, 
            "android.os.Parcel.writeInt": 15, 
            "java.security.KeyFactory": 2, 
            "java.lang.String.contains": 14, 
            "android.os.Parcel.writeString": 14, 
            "android.os.Bundle.getStringArrayList": 4, 
            "android.webkit.WebView.postUrl": 1, 
            "android.content.Context.getPackageName": 7, 
            "android.app.Activity.onSaveInstanceState": 1, 
            "java.lang.String.toUpperCase": 3, 
            "android.webkit.WebSettings.getUserAgentString": 1, 
            "android.widget.Button.setSelected": 7, 
            "java.security.Signature": 4, 
            "java.security.Signature.initVerify": 1, 
            "android.content.Context.getApplicationContext": 1, 
            "android.webkit.WebView.getSettings": 2, 
            "android.os.RemoteException": 2, 
            "android.app.Activity.onKeyDown": 1, 
            "android.os.Parcel.readInt": 11, 
            "android.os.Parcel.enforceInterface": 5, 
            "android.content.Context.bindService": 1, 
            "android.net.Uri": 2, 
            "android.content.Context.unbindService": 1, 
            "android.os.IBinder": 6, 
            "java.util.Locale.getCountry": 1, 
            "android.os.Bundle.getString": 1, 
            "android.webkit.WebSettings.setUserAgentString": 1, 
            "android.os.IBinder.queryLocalInterface": 1, 
            "java.lang.Long": 2, 
            "java.lang.StringBuilder": 312, 
            "java.security.Signature.getInstance": 1, 
            "android.app.Activity.onRestoreInstanceState": 1, 
            "java.lang.String.equalsIgnoreCase": 1, 
            "java.util.Locale.getLanguage": 1, 
            "android.content.pm.PackageManager": 2, 
            "java.lang.System": 1, 
            "android.os.Bundle.toString": 1, 
            "android.os.Bundle": 18, 
            "android.widget.Button.getText": 1, 
            "android.util.Log": 42, 
            "org.json.JSONObject.optString": 11, 
            "android.widget.RelativeLayout": 2, 
            "java.lang.String.split": 3, 
            "android.view.MotionEvent": 1, 
            "java.lang.String.equals": 14, 
            "android.os.Bundle.getParcelable": 1, 
            "java.lang.Integer": 9, 
            "java.lang.Integer.toString": 1, 
            "java.security.KeyFactory.getInstance": 1, 
            "android.app.AlertDialog": 2, 
            "java.net.URLEncoder": 4, 
            "android.app.Activity.startIntentSenderForResult": 1, 
            "android.view.Window": 1, 
            "java.lang.StringBuilder.append": 227, 
            "android.os.Bundle.writeToParcel": 4, 
            "java.lang.String.replace": 3, 
            "java.security.MessageDigest.update": 1, 
            "org.json.JSONObject": 13, 
            "android.os.Binder": 1, 
            "android.os.Parcel": 103, 
            "android.os.Parcel.writeInterfaceToken": 5, 
            "android.webkit.WebView.loadUrl": 9, 
            "android.os.Parcel.recycle": 20, 
            "android.widget.Button": 9, 
            "android.webkit.WebSettings": 5, 
            "java.security.Signature.update": 1, 
            "android.os.Bundle.containsKey": 4, 
            "java.lang.String.startsWith": 1, 
            "java.lang.String": 51, 
            "org.json.JSONObject.optInt": 1, 
            "android.content.pm.PackageManager.getPackageInfo": 1, 
            "android.app.Activity.onConfigurationChanged": 1, 
            "java.lang.Integer.intValue": 5, 
            "android.os.Parcel.readString": 13, 
            "java.lang.String.getBytes": 4, 
            "java.lang.Thread": 2, 
            "android.content.Intent.getExtras": 3, 
            "android.app.Activity.onActivityResult": 1, 
            "android.widget.LinearLayout.setVisibility": 4, 
            "java.security.MessageDigest.getInstance": 1, 
            "android.webkit.WebView.setWebChromeClient": 1
        }, 
        "Strings": {
            "http://m.touringplans.com/wdw/in-app-product-redirect": 2, 
            "0swa1D": 2, 
            "launchPurchaseFlow": 2, 
            "Showing alert dialog:": 1, 
            "http://m.touringplans.com/wdw/parks/3": 1, 
            "http://m.touringplans.com/wdw/parks/2": 1, 
            "http://m.touringplans.com/wdw/ten_day": 1, 
            "http://m.touringplans.com/wdw/parks/4": 1, 
            "ERROR NO SUCH ALGORITHM EXCEPTION": 1, 
            "JavaScript dialog": 1, 
            "com.android.vending.billing.InAppBillingService.BIND": 1, 
            "Intent with no response code, assuming OK (known issue)": 1, 
            "Unable to buy item": 1, 
            "Error consuming consuming sku": 1, 
            "android_id": 2, 
            "wdw/parks/2": 1, 
            "consume": 4, 
            "Checking for in-app billing 3 support.": 1, 
            "com.touringplans.lines.wdw.oneyear": 1, 
            ". Request code:": 1, 
            "title": 1, 
            "Initial inventory query finished; enabling main UI.": 1, 
            "description": 1, 
            "BUY_INTENT": 1, 
            "INAPP_PURCHASE_DATA": 1, 
            ",": 2, 
            "androidLines/": 1, 
            "http://m.touringplans.com/wdw/parks/1": 1, 
            "data is null": 1, 
            "&confirm=": 1, 
            "Constructing buy intent for": 1, 
            "Ending async operation:": 1, 
            "http://m.touringplans.com/wdw/chats": 1, 
            "Query inventory finished.": 1, 
            ":Unknown IAB Helper Error": 1, 
            "Subscriptions NOT AVAILABLE. Response:": 1, 
            ", purchase:": 1, 
            "Unknown purchase response.": 1, 
            "Result code was OK but in-app billing response was not OK:": 1, 
            "Error:": 1, 
            "queryPrices: nothing to do because there are no SKUs.": 1, 
            "Billing service disconnected.": 1, 
            "Purchase is present, and we consume everything immediately. Starting consumption.": 1, 
            "Bundle with null response code, assuming OK (known issue)": 1, 
            "Continuation token:": 1, 
            "urlSplit:": 1, 
            "RemoteException while setting up in-app billing.": 1, 
            "Unexpected type for intent response code.": 1, 
            "in-app-purchase": 1, 
            "Error purchasing:": 1, 
            "wdw:": 1, 
            "OK": 1, 
            "Successful resultcode from purchase activity.": 1, 
            "Disposing.": 1, 
            "Creating IAB helper.": 1, 
            "IabHelper": 1, 
            "Unbinding from service.": 1, 
            "token": 1, 
            "Null data in IAB activity result.": 1, 
            "&product_id=": 1, 
            "padding byte \\'=\\' falsely signals end of encoded value at offset": 1, 
            "IAB helper is not set up. Can\\'t perform operation:": 1, 
            "IAB helper created.": 1, 
            "Can\\'t start async operation (": 1, 
            "Consumption finished. Purchase:": 1, 
            "com.android.vending.billing.IInAppBillingService": 14, 
            "Remote exception while refreshing inventory.": 1, 
            "Billing service unavailable on device.": 1, 
            "IAB helper is already set up.": 1, 
            "HS": 1, 
            "inapp": 6, 
            "wdw/parks/4": 1, 
            "Subscriptions are not available.": 1, 
            "INAPP_PURCHASE_DATA_LIST": 2, 
            "Starting in-app billing setup.": 1, 
            "wdw/parks/3": 1, 
            "! Consuming it!": 1, 
            "ITEM_ID_LIST": 1, 
            "0:OK/-1001:Remote exception during initialization/-1002:Bad response received/-1003:Purchase signature verification failed/-1004:Send intent failed/-1005:User cancelled/-1006:Unknown purchase response/-1007:Missing token/-1008:Unknown error/-1009:Subscriptions not available/-1010:Invalid consumption attempt": 1, 
            "SkuDetails:": 1, 
            "Illegal state for operation (": 1, 
            "Launching mWebView activity for external URL": 1, 
            "****": 1, 
            "Signature exception.": 1, 
            "/": 5, 
            "android.intent.action.VIEW": 2, 
            "Purchase failed. Result code:": 1, 
            "Package name:": 1, 
            "Purchase data:": 3, 
            "Inventory refresh successful.": 1, 
            "AK": 1, 
            "Bundle returned from getPurchases() doesn\\'t contain required fields.": 1, 
            ") because another async operation(": 1, 
            "NoSuchAlgorithmException.": 1, 
            "Launching buy intent for": 1, 
            "handleActivityResult": 1, 
            "10-Day": 1, 
            "purchaseState": 1, 
            "Remote exception while starting purchase flow": 1, 
            "EP": 1, 
            "Setup successful.": 1, 
            "\\\\?": 1, 
            "product_id": 1, 
            "(response:": 1, 
            "%region%": 2, 
            "packageName": 1, 
            ", item type:": 1, 
            "SHA1withRSA": 1, 
            "INAPP_DATA_SIGNATURE": 1, 
            "MK": 1, 
            "Error refreshing inventory (querying prices of items).": 1, 
            "Starting async operation:": 1, 
            "Bad Base64 input character at": 1, 
            "PurchaseInfo(type:": 1, 
            "Chat": 1, 
            ". No token.": 1, 
            "Problem purchashing item.": 1, 
            "login": 1, 
            "(decimal)": 1, 
            "Signature:": 1, 
            "getPurchases() failed:": 1, 
            "IAB returned null purchaseData or dataSignature": 1, 
            "Extras:": 2, 
            "):": 1, 
            "subs": 5, 
            "Expected item type:": 1, 
            "Purchase canceled - Response:": 1, 
            "property=": 1, 
            "Home": 1, 
            "single trailing character at offset": 1, 
            "Error refreshing inventory (querying owned subscriptions).": 1, 
            "Successfully consumed sku:": 1, 
            "Destroying IAB helper.": 1, 
            "Querying owned items, item type:": 1, 
            "Successful consume of sku": 1, 
            "IAB setup successful.": 1, 
            "In-app billing error:": 1, 
            ":Unknown": 1, 
            "): IAB helper is not set up.": 1, 
            "IABUtil/Security": 9, 
            "Error parsing JSON response while refreshing inventory.": 1, 
            "Intercepted URL:": 1, 
            "Problem setting up In-app Billing:": 1, 
            "Purchase signature verification **FAILED**. Not adding item.": 1, 
            ".": 1, 
            ". Response:": 1, 
            "End consumption flow.": 1, 
            "http://m.touringplans.com/wdw/plans": 1, 
            ":": 5, 
            "type": 1, 
            "orderId": 1, 
            "Success": 1, 
            "\\' can\\'t be consumed.": 1, 
            ") is in progress.": 1, 
            "INAPP_CONTINUATION_TOKEN": 1, 
            ", result:": 1, 
            "Items of type \\'": 1, 
            "Error while consuming:": 1, 
            "Got sku details:": 1, 
            "Found": 1, 
            "In-app billing warning:": 1, 
            "DETAILS_LIST": 2, 
            "http://m.touringplans.com/wdw": 3, 
            "Unexpected type for intent response code:": 1, 
            "Base64 decoding failed.": 2, 
            "SHA-1": 1, 
            "Parks": 1, 
            "BUG: empty/null token!": 1, 
            "http://m.touringplans.com/wdw/purchased/verify": 1, 
            "http://m.touringplans.com": 1, 
            "INAPP_DATA_SIGNATURE_LIST": 2, 
            "0:OK/1:User Canceled/2:Unknown/3:Billing Unavailable/4:Item unavailable/5:Developer Error/6:Error/7:Item Already Owned/8:Item not owned": 1, 
            "In-app billing version 3 supported for": 1, 
            "signature does not match data.": 1, 
            "Purchase signature verification FAILED for sku": 1, 
            "Query inventory was successful.": 1, 
            "Data signature:": 1, 
            "onActivityResult(": 1, 
            "com.touringplans.lines.wdw.onemonth": 1, 
            "PRODUCT ID:": 1, 
            "RESPONSE_CODE": 2, 
            "wdw/parks/1": 1, 
            "refresh inventory": 1, 
            "invalid padding byte \\'=\\' at byte offset": 1, 
            "Error refreshing inventory (querying owned items).": 1, 
            "chat": 1, 
            "MIGfMA0GCSqGSIb3DQEBAQUAA4GNADCBiQKBgQCQCBgsGr1fv5J2vbOfWffldy6jSXGUALHJ9+gjpLIFFG+3L5InP0smPOm3m8xOOEzn1vqtOiCXNvwL0wz6Vt4B7Brc3OZhs8NF6FvJk7wUGCn7Sn4vL6XfwRU/ZtMAkCd3n+Rh59ahDOieaomJXIpBgQhr4PzuA+wwJUjXLzXpKwIDAQAB": 1, 
            ", token:": 1, 
            "Querying SKU details.": 1, 
            "Signature verification failed.": 1, 
            "Subscriptions AVAILABLE.": 1, 
            "RemoteException while launching purchase flow for sku": 1, 
            "Lines Error:": 1, 
            "Failed to parse purchase data.": 2, 
            "UTF-8": 5, 
            "User canceled.": 1, 
            "Purchase finished:": 1, 
            "Failed to query inventory:": 1, 
            "encoded value has invalid trailing byte": 1, 
            "iso-8859-1": 1, 
            "Remote exception while consuming. PurchaseInfo:": 1, 
            "Error purchasing. Authenticity verification failed.": 1, 
            "Sku is owned:": 1, 
            "Owned items response:": 1, 
            "Error refreshing inventory (querying prices of subscriptions).": 1, 
            ")": 1, 
            "Signature verification failed for sku": 1, 
            "purchaseTime": 1, 
            "BASE64": 1, 
            "IabResult:": 1, 
            "parks": 1, 
            "getSkuDetails() failed:": 1, 
            "&receipt_id=": 1, 
            "Error checking for billing v3 support.": 1, 
            "Consuming sku:": 1, 
            "Calling getPurchases with continuation token:": 1, 
            "queryInventory": 2, 
            "productId": 2, 
            "&identifier=": 1, 
            "plans": 1, 
            "Billing service connected.": 1, 
            "Error consuming sku": 1, 
            "BUG: either purchaseData or dataSignature is null.": 1, 
            "getSkuDetails() returned a bundle with neither an error nor a detail list.": 1, 
            "developerPayload": 1, 
            "%lang%": 2, 
            "price": 1, 
            "wdw": 6, 
            "Lines": 2, 
            "INAPP_PURCHASE_ITEM_LIST": 2, 
            "SendIntentException while launching purchase flow for sku": 1, 
            "Purchase signature successfully verified.": 1, 
            "Can\\'t consume": 1, 
            "Exception:": 1, 
            "http://m.touringplans.com/": 2, 
            "Plans": 1, 
            "Unexpected type for bundle response code:": 1, 
            "Failed to send intent.": 1, 
            "Consumption successful. Provisioning.": 1, 
            "purchaseToken": 1, 
            "Unable to buy item, Error response:": 1, 
            "ten_day": 1, 
            "RSA": 1, 
            "Null data in IAB result": 1, 
            "PurchaseInfo is missing token for sku:": 1, 
            "Launching purchase flow for subscription.": 1, 
            "com.touringplans.lines.wdw.oneweek": 1, 
            "Unexpected type for bundle response code.": 1, 
            "Invalid key specification.": 2, 
            "onActivityResult handled by IABUtil.": 1, 
            "Purchase successful.": 1, 
            "HASH:": 1
        }, 
        "API packages": {
            "android.app": 18, 
            "android.webkit": 46, 
            "java.util": 5, 
            "android.content": 30, 
            "android.widget": 28, 
            "android.util": 82, 
            "java.lang": 663, 
            "org.json": 26, 
            "android.os": 248, 
            "java.security": 15, 
            "android.text": 3, 
            "java.net": 5, 
            "android.net": 2, 
            "android.content.pm": 3, 
            "android.view": 2
        }, 
        "System commands": {}, 
        "Intents": {
            "android.intent.action.MAIN": 1
        }, 
        "Activities": {
            "com.touringplans.lines.android.WDWLines": [
                "android.intent.action.MAIN"
            ]
        }, 
        "Services": {}, 
        "Receivers": {}, 
        "FlowDroid": {
            "SMS_MMS": {
                "SMS_MMS": 0, 
                "FILE_INFORMATION": 0, 
                "UNIQUE_IDENTIFIER": 0, 
                "FILE": 0, 
                "SYNCHRONIZATION_DATA": 0, 
                "BLUETOOTH_INFORMATION": 0, 
                "EMAIL": 0, 
                "VOIP": 0, 
                "LOG": 0, 
                "IMAGE": 0, 
                "DATABASE_INFORMATION": 0, 
                "ACCOUNT_SETTINGS": 0, 
                "VIDEO": 0, 
                "PHONE_CONNECTION": 0, 
                "CALENDAR_INFORMATION": 0, 
                "WIDGET": 0, 
                "NFC": 0, 
                "LOCATION_INFORMATION": 0, 
                "BUNDLE": 0, 
                "BROWSER_INFORMATION": 0, 
                "SYSTEM_SETTINGS": 0, 
                "AUDIO": 0, 
                "PHONE_STATE": 0, 
                "IPC": 0, 
                "NOT_EXISTING": 0, 
                "ACCOUNT_INFORMATION": 0, 
                "BLUETOOTH": 0, 
                "CONTACT_INFORMATION": 0, 
                "NO_CATEGORY": 0, 
                "NETWORK_INFORMATION": 0, 
                "NETWORK": 0
            }, 
            "FILE_INFORMATION": {
                "SMS_MMS": 0, 
                "FILE_INFORMATION": 0, 
                "UNIQUE_IDENTIFIER": 0, 
                "FILE": 0, 
                "SYNCHRONIZATION_DATA": 0, 
                "BLUETOOTH_INFORMATION": 0, 
                "EMAIL": 0, 
                "VOIP": 0, 
                "LOG": 0, 
                "IMAGE": 0, 
                "DATABASE_INFORMATION": 0, 
                "ACCOUNT_SETTINGS": 0, 
                "VIDEO": 0, 
                "PHONE_CONNECTION": 0, 
                "CALENDAR_INFORMATION": 0, 
                "WIDGET": 0, 
                "NFC": 0, 
                "LOCATION_INFORMATION": 0, 
                "BUNDLE": 0, 
                "BROWSER_INFORMATION": 0, 
                "SYSTEM_SETTINGS": 0, 
                "AUDIO": 0, 
                "PHONE_STATE": 0, 
                "IPC": 0, 
                "NOT_EXISTING": 0, 
                "ACCOUNT_INFORMATION": 0, 
                "BLUETOOTH": 0, 
                "CONTACT_INFORMATION": 0, 
                "NO_CATEGORY": 0, 
                "NETWORK_INFORMATION": 0, 
                "NETWORK": 0
            }, 
            "UNIQUE_IDENTIFIER": {
                "SMS_MMS": 0, 
                "FILE_INFORMATION": 0, 
                "UNIQUE_IDENTIFIER": 0, 
                "FILE": 0, 
                "SYNCHRONIZATION_DATA": 0, 
                "BLUETOOTH_INFORMATION": 0, 
                "EMAIL": 0, 
                "VOIP": 0, 
                "LOG": 0, 
                "IMAGE": 0, 
                "DATABASE_INFORMATION": 0, 
                "ACCOUNT_SETTINGS": 0, 
                "VIDEO": 0, 
                "PHONE_CONNECTION": 0, 
                "CALENDAR_INFORMATION": 0, 
                "WIDGET": 0, 
                "NFC": 0, 
                "LOCATION_INFORMATION": 0, 
                "BUNDLE": 0, 
                "BROWSER_INFORMATION": 0, 
                "SYSTEM_SETTINGS": 0, 
                "AUDIO": 0, 
                "PHONE_STATE": 0, 
                "IPC": 0, 
                "NOT_EXISTING": 0, 
                "ACCOUNT_INFORMATION": 0, 
                "BLUETOOTH": 0, 
                "CONTACT_INFORMATION": 0, 
                "NO_CATEGORY": 0, 
                "NETWORK_INFORMATION": 0, 
                "NETWORK": 0
            }, 
            "FILE": {
                "SMS_MMS": 0, 
                "FILE_INFORMATION": 0, 
                "UNIQUE_IDENTIFIER": 0, 
                "FILE": 0, 
                "SYNCHRONIZATION_DATA": 0, 
                "BLUETOOTH_INFORMATION": 0, 
                "EMAIL": 0, 
                "VOIP": 0, 
                "LOG": 0, 
                "IMAGE": 0, 
                "DATABASE_INFORMATION": 0, 
                "ACCOUNT_SETTINGS": 0, 
                "VIDEO": 0, 
                "PHONE_CONNECTION": 0, 
                "CALENDAR_INFORMATION": 0, 
                "WIDGET": 0, 
                "NFC": 0, 
                "LOCATION_INFORMATION": 0, 
                "BUNDLE": 0, 
                "BROWSER_INFORMATION": 0, 
                "SYSTEM_SETTINGS": 0, 
                "AUDIO": 0, 
                "PHONE_STATE": 0, 
                "IPC": 0, 
                "NOT_EXISTING": 0, 
                "ACCOUNT_INFORMATION": 0, 
                "BLUETOOTH": 0, 
                "CONTACT_INFORMATION": 0, 
                "NO_CATEGORY": 0, 
                "NETWORK_INFORMATION": 0, 
                "NETWORK": 0
            }, 
            "SYNCHRONIZATION_DATA": {
                "SMS_MMS": 0, 
                "FILE_INFORMATION": 0, 
                "UNIQUE_IDENTIFIER": 0, 
                "FILE": 0, 
                "SYNCHRONIZATION_DATA": 0, 
                "BLUETOOTH_INFORMATION": 0, 
                "EMAIL": 0, 
                "VOIP": 0, 
                "LOG": 0, 
                "IMAGE": 0, 
                "DATABASE_INFORMATION": 0, 
                "ACCOUNT_SETTINGS": 0, 
                "VIDEO": 0, 
                "PHONE_CONNECTION": 0, 
                "CALENDAR_INFORMATION": 0, 
                "WIDGET": 0, 
                "NFC": 0, 
                "LOCATION_INFORMATION": 0, 
                "BUNDLE": 0, 
                "BROWSER_INFORMATION": 0, 
                "SYSTEM_SETTINGS": 0, 
                "AUDIO": 0, 
                "PHONE_STATE": 0, 
                "IPC": 0, 
                "NOT_EXISTING": 0, 
                "ACCOUNT_INFORMATION": 0, 
                "BLUETOOTH": 0, 
                "CONTACT_INFORMATION": 0, 
                "NO_CATEGORY": 0, 
                "NETWORK_INFORMATION": 0, 
                "NETWORK": 0
            }, 
            "BLUETOOTH_INFORMATION": {
                "SMS_MMS": 0, 
                "FILE_INFORMATION": 0, 
                "UNIQUE_IDENTIFIER": 0, 
                "FILE": 0, 
                "SYNCHRONIZATION_DATA": 0, 
                "BLUETOOTH_INFORMATION": 0, 
                "EMAIL": 0, 
                "VOIP": 0, 
                "LOG": 0, 
                "IMAGE": 0, 
                "DATABASE_INFORMATION": 0, 
                "ACCOUNT_SETTINGS": 0, 
                "VIDEO": 0, 
                "PHONE_CONNECTION": 0, 
                "CALENDAR_INFORMATION": 0, 
                "WIDGET": 0, 
                "NFC": 0, 
                "LOCATION_INFORMATION": 0, 
                "BUNDLE": 0, 
                "BROWSER_INFORMATION": 0, 
                "SYSTEM_SETTINGS": 0, 
                "AUDIO": 0, 
                "PHONE_STATE": 0, 
                "IPC": 0, 
                "NOT_EXISTING": 0, 
                "ACCOUNT_INFORMATION": 0, 
                "BLUETOOTH": 0, 
                "CONTACT_INFORMATION": 0, 
                "NO_CATEGORY": 0, 
                "NETWORK_INFORMATION": 0, 
                "NETWORK": 0
            }, 
            "EMAIL": {
                "SMS_MMS": 0, 
                "FILE_INFORMATION": 0, 
                "UNIQUE_IDENTIFIER": 0, 
                "FILE": 0, 
                "SYNCHRONIZATION_DATA": 0, 
                "BLUETOOTH_INFORMATION": 0, 
                "EMAIL": 0, 
                "VOIP": 0, 
                "LOG": 0, 
                "IMAGE": 0, 
                "DATABASE_INFORMATION": 0, 
                "ACCOUNT_SETTINGS": 0, 
                "VIDEO": 0, 
                "PHONE_CONNECTION": 0, 
                "CALENDAR_INFORMATION": 0, 
                "WIDGET": 0, 
                "NFC": 0, 
                "LOCATION_INFORMATION": 0, 
                "BUNDLE": 0, 
                "BROWSER_INFORMATION": 0, 
                "SYSTEM_SETTINGS": 0, 
                "AUDIO": 0, 
                "PHONE_STATE": 0, 
                "IPC": 0, 
                "NOT_EXISTING": 0, 
                "ACCOUNT_INFORMATION": 0, 
                "BLUETOOTH": 0, 
                "CONTACT_INFORMATION": 0, 
                "NO_CATEGORY": 0, 
                "NETWORK_INFORMATION": 0, 
                "NETWORK": 0
            }, 
            "VOIP": {
                "SMS_MMS": 0, 
                "FILE_INFORMATION": 0, 
                "UNIQUE_IDENTIFIER": 0, 
                "FILE": 0, 
                "SYNCHRONIZATION_DATA": 0, 
                "BLUETOOTH_INFORMATION": 0, 
                "EMAIL": 0, 
                "VOIP": 0, 
                "LOG": 0, 
                "IMAGE": 0, 
                "DATABASE_INFORMATION": 0, 
                "ACCOUNT_SETTINGS": 0, 
                "VIDEO": 0, 
                "PHONE_CONNECTION": 0, 
                "CALENDAR_INFORMATION": 0, 
                "WIDGET": 0, 
                "NFC": 0, 
                "LOCATION_INFORMATION": 0, 
                "BUNDLE": 0, 
                "BROWSER_INFORMATION": 0, 
                "SYSTEM_SETTINGS": 0, 
                "AUDIO": 0, 
                "PHONE_STATE": 0, 
                "IPC": 0, 
                "NOT_EXISTING": 0, 
                "ACCOUNT_INFORMATION": 0, 
                "BLUETOOTH": 0, 
                "CONTACT_INFORMATION": 0, 
                "NO_CATEGORY": 0, 
                "NETWORK_INFORMATION": 0, 
                "NETWORK": 0
            }, 
            "LOG": {
                "SMS_MMS": 0, 
                "FILE_INFORMATION": 0, 
                "UNIQUE_IDENTIFIER": 0, 
                "FILE": 0, 
                "SYNCHRONIZATION_DATA": 0, 
                "BLUETOOTH_INFORMATION": 0, 
                "EMAIL": 0, 
                "VOIP": 0, 
                "LOG": 0, 
                "IMAGE": 0, 
                "DATABASE_INFORMATION": 0, 
                "ACCOUNT_SETTINGS": 0, 
                "VIDEO": 0, 
                "PHONE_CONNECTION": 0, 
                "CALENDAR_INFORMATION": 0, 
                "WIDGET": 0, 
                "NFC": 0, 
                "LOCATION_INFORMATION": 0, 
                "BUNDLE": 0, 
                "BROWSER_INFORMATION": 0, 
                "SYSTEM_SETTINGS": 0, 
                "AUDIO": 0, 
                "PHONE_STATE": 0, 
                "IPC": 0, 
                "NOT_EXISTING": 0, 
                "ACCOUNT_INFORMATION": 0, 
                "BLUETOOTH": 0, 
                "CONTACT_INFORMATION": 0, 
                "NO_CATEGORY": 0, 
                "NETWORK_INFORMATION": 0, 
                "NETWORK": 0
            }, 
            "IMAGE": {
                "SMS_MMS": 0, 
                "FILE_INFORMATION": 0, 
                "UNIQUE_IDENTIFIER": 0, 
                "FILE": 0, 
                "SYNCHRONIZATION_DATA": 0, 
                "BLUETOOTH_INFORMATION": 0, 
                "EMAIL": 0, 
                "VOIP": 0, 
                "LOG": 0, 
                "IMAGE": 0, 
                "DATABASE_INFORMATION": 0, 
                "ACCOUNT_SETTINGS": 0, 
                "VIDEO": 0, 
                "PHONE_CONNECTION": 0, 
                "CALENDAR_INFORMATION": 0, 
                "WIDGET": 0, 
                "NFC": 0, 
                "LOCATION_INFORMATION": 0, 
                "BUNDLE": 0, 
                "BROWSER_INFORMATION": 0, 
                "SYSTEM_SETTINGS": 0, 
                "AUDIO": 0, 
                "PHONE_STATE": 0, 
                "IPC": 0, 
                "NOT_EXISTING": 0, 
                "ACCOUNT_INFORMATION": 0, 
                "BLUETOOTH": 0, 
                "CONTACT_INFORMATION": 0, 
                "NO_CATEGORY": 0, 
                "NETWORK_INFORMATION": 0, 
                "NETWORK": 0
            }, 
            "DATABASE_INFORMATION": {
                "SMS_MMS": 0, 
                "FILE_INFORMATION": 0, 
                "UNIQUE_IDENTIFIER": 0, 
                "FILE": 0, 
                "SYNCHRONIZATION_DATA": 0, 
                "BLUETOOTH_INFORMATION": 0, 
                "EMAIL": 0, 
                "VOIP": 0, 
                "LOG": 0, 
                "IMAGE": 0, 
                "DATABASE_INFORMATION": 0, 
                "ACCOUNT_SETTINGS": 0, 
                "VIDEO": 0, 
                "PHONE_CONNECTION": 0, 
                "CALENDAR_INFORMATION": 0, 
                "WIDGET": 0, 
                "NFC": 0, 
                "LOCATION_INFORMATION": 0, 
                "BUNDLE": 0, 
                "BROWSER_INFORMATION": 0, 
                "SYSTEM_SETTINGS": 0, 
                "AUDIO": 0, 
                "PHONE_STATE": 0, 
                "IPC": 0, 
                "NOT_EXISTING": 0, 
                "ACCOUNT_INFORMATION": 0, 
                "BLUETOOTH": 0, 
                "CONTACT_INFORMATION": 0, 
                "NO_CATEGORY": 0, 
                "NETWORK_INFORMATION": 0, 
                "NETWORK": 0
            }, 
            "ACCOUNT_SETTINGS": {
                "SMS_MMS": 0, 
                "FILE_INFORMATION": 0, 
                "UNIQUE_IDENTIFIER": 0, 
                "FILE": 0, 
                "SYNCHRONIZATION_DATA": 0, 
                "BLUETOOTH_INFORMATION": 0, 
                "EMAIL": 0, 
                "VOIP": 0, 
                "LOG": 0, 
                "IMAGE": 0, 
                "DATABASE_INFORMATION": 0, 
                "ACCOUNT_SETTINGS": 0, 
                "VIDEO": 0, 
                "PHONE_CONNECTION": 0, 
                "CALENDAR_INFORMATION": 0, 
                "WIDGET": 0, 
                "NFC": 0, 
                "LOCATION_INFORMATION": 0, 
                "BUNDLE": 0, 
                "BROWSER_INFORMATION": 0, 
                "SYSTEM_SETTINGS": 0, 
                "AUDIO": 0, 
                "PHONE_STATE": 0, 
                "IPC": 0, 
                "NOT_EXISTING": 0, 
                "ACCOUNT_INFORMATION": 0, 
                "BLUETOOTH": 0, 
                "CONTACT_INFORMATION": 0, 
                "NO_CATEGORY": 0, 
                "NETWORK_INFORMATION": 0, 
                "NETWORK": 0
            }, 
            "VIDEO": {
                "SMS_MMS": 0, 
                "FILE_INFORMATION": 0, 
                "UNIQUE_IDENTIFIER": 0, 
                "FILE": 0, 
                "SYNCHRONIZATION_DATA": 0, 
                "BLUETOOTH_INFORMATION": 0, 
                "EMAIL": 0, 
                "VOIP": 0, 
                "LOG": 0, 
                "IMAGE": 0, 
                "DATABASE_INFORMATION": 0, 
                "ACCOUNT_SETTINGS": 0, 
                "VIDEO": 0, 
                "PHONE_CONNECTION": 0, 
                "CALENDAR_INFORMATION": 0, 
                "WIDGET": 0, 
                "NFC": 0, 
                "LOCATION_INFORMATION": 0, 
                "BUNDLE": 0, 
                "BROWSER_INFORMATION": 0, 
                "SYSTEM_SETTINGS": 0, 
                "AUDIO": 0, 
                "PHONE_STATE": 0, 
                "IPC": 0, 
                "NOT_EXISTING": 0, 
                "ACCOUNT_INFORMATION": 0, 
                "BLUETOOTH": 0, 
                "CONTACT_INFORMATION": 0, 
                "NO_CATEGORY": 0, 
                "NETWORK_INFORMATION": 0, 
                "NETWORK": 0
            }, 
            "PHONE_CONNECTION": {
                "SMS_MMS": 0, 
                "FILE_INFORMATION": 0, 
                "UNIQUE_IDENTIFIER": 0, 
                "FILE": 0, 
                "SYNCHRONIZATION_DATA": 0, 
                "BLUETOOTH_INFORMATION": 0, 
                "EMAIL": 0, 
                "VOIP": 0, 
                "LOG": 0, 
                "IMAGE": 0, 
                "DATABASE_INFORMATION": 0, 
                "ACCOUNT_SETTINGS": 0, 
                "VIDEO": 0, 
                "PHONE_CONNECTION": 0, 
                "CALENDAR_INFORMATION": 0, 
                "WIDGET": 0, 
                "NFC": 0, 
                "LOCATION_INFORMATION": 0, 
                "BUNDLE": 0, 
                "BROWSER_INFORMATION": 0, 
                "SYSTEM_SETTINGS": 0, 
                "AUDIO": 0, 
                "PHONE_STATE": 0, 
                "IPC": 0, 
                "NOT_EXISTING": 0, 
                "ACCOUNT_INFORMATION": 0, 
                "BLUETOOTH": 0, 
                "CONTACT_INFORMATION": 0, 
                "NO_CATEGORY": 0, 
                "NETWORK_INFORMATION": 0, 
                "NETWORK": 0
            }, 
            "CALENDAR_INFORMATION": {
                "SMS_MMS": 0, 
                "FILE_INFORMATION": 0, 
                "UNIQUE_IDENTIFIER": 0, 
                "FILE": 0, 
                "SYNCHRONIZATION_DATA": 0, 
                "BLUETOOTH_INFORMATION": 0, 
                "EMAIL": 0, 
                "VOIP": 0, 
                "LOG": 0, 
                "IMAGE": 0, 
                "DATABASE_INFORMATION": 0, 
                "ACCOUNT_SETTINGS": 0, 
                "VIDEO": 0, 
                "PHONE_CONNECTION": 0, 
                "CALENDAR_INFORMATION": 0, 
                "WIDGET": 0, 
                "NFC": 0, 
                "LOCATION_INFORMATION": 0, 
                "BUNDLE": 0, 
                "BROWSER_INFORMATION": 0, 
                "SYSTEM_SETTINGS": 0, 
                "AUDIO": 0, 
                "PHONE_STATE": 0, 
                "IPC": 0, 
                "NOT_EXISTING": 0, 
                "ACCOUNT_INFORMATION": 0, 
                "BLUETOOTH": 0, 
                "CONTACT_INFORMATION": 0, 
                "NO_CATEGORY": 0, 
                "NETWORK_INFORMATION": 0, 
                "NETWORK": 0
            }, 
            "WIDGET": {
                "SMS_MMS": 0, 
                "FILE_INFORMATION": 0, 
                "UNIQUE_IDENTIFIER": 0, 
                "FILE": 0, 
                "SYNCHRONIZATION_DATA": 0, 
                "BLUETOOTH_INFORMATION": 0, 
                "EMAIL": 0, 
                "VOIP": 0, 
                "LOG": 0, 
                "IMAGE": 0, 
                "DATABASE_INFORMATION": 0, 
                "ACCOUNT_SETTINGS": 0, 
                "VIDEO": 0, 
                "PHONE_CONNECTION": 0, 
                "CALENDAR_INFORMATION": 0, 
                "WIDGET": 0, 
                "NFC": 0, 
                "LOCATION_INFORMATION": 0, 
                "BUNDLE": 0, 
                "BROWSER_INFORMATION": 0, 
                "SYSTEM_SETTINGS": 0, 
                "AUDIO": 0, 
                "PHONE_STATE": 0, 
                "IPC": 0, 
                "NOT_EXISTING": 0, 
                "ACCOUNT_INFORMATION": 0, 
                "BLUETOOTH": 0, 
                "CONTACT_INFORMATION": 0, 
                "NO_CATEGORY": 0, 
                "NETWORK_INFORMATION": 0, 
                "NETWORK": 0
            }, 
            "NFC": {
                "SMS_MMS": 0, 
                "FILE_INFORMATION": 0, 
                "UNIQUE_IDENTIFIER": 0, 
                "FILE": 0, 
                "SYNCHRONIZATION_DATA": 0, 
                "BLUETOOTH_INFORMATION": 0, 
                "EMAIL": 0, 
                "VOIP": 0, 
                "LOG": 0, 
                "IMAGE": 0, 
                "DATABASE_INFORMATION": 0, 
                "ACCOUNT_SETTINGS": 0, 
                "VIDEO": 0, 
                "PHONE_CONNECTION": 0, 
                "CALENDAR_INFORMATION": 0, 
                "WIDGET": 0, 
                "NFC": 0, 
                "LOCATION_INFORMATION": 0, 
                "BUNDLE": 0, 
                "BROWSER_INFORMATION": 0, 
                "SYSTEM_SETTINGS": 0, 
                "AUDIO": 0, 
                "PHONE_STATE": 0, 
                "IPC": 0, 
                "NOT_EXISTING": 0, 
                "ACCOUNT_INFORMATION": 0, 
                "BLUETOOTH": 0, 
                "CONTACT_INFORMATION": 0, 
                "NO_CATEGORY": 0, 
                "NETWORK_INFORMATION": 0, 
                "NETWORK": 0
            }, 
            "LOCATION_INFORMATION": {
                "SMS_MMS": 0, 
                "FILE_INFORMATION": 0, 
                "UNIQUE_IDENTIFIER": 0, 
                "FILE": 0, 
                "SYNCHRONIZATION_DATA": 0, 
                "BLUETOOTH_INFORMATION": 0, 
                "EMAIL": 0, 
                "VOIP": 0, 
                "LOG": 0, 
                "IMAGE": 0, 
                "DATABASE_INFORMATION": 0, 
                "ACCOUNT_SETTINGS": 0, 
                "VIDEO": 0, 
                "PHONE_CONNECTION": 0, 
                "CALENDAR_INFORMATION": 0, 
                "WIDGET": 0, 
                "NFC": 0, 
                "LOCATION_INFORMATION": 0, 
                "BUNDLE": 0, 
                "BROWSER_INFORMATION": 0, 
                "SYSTEM_SETTINGS": 0, 
                "AUDIO": 0, 
                "PHONE_STATE": 0, 
                "IPC": 0, 
                "NOT_EXISTING": 0, 
                "ACCOUNT_INFORMATION": 0, 
                "BLUETOOTH": 0, 
                "CONTACT_INFORMATION": 0, 
                "NO_CATEGORY": 0, 
                "NETWORK_INFORMATION": 0, 
                "NETWORK": 0
            }, 
            "BUNDLE": {
                "SMS_MMS": 0, 
                "FILE_INFORMATION": 0, 
                "UNIQUE_IDENTIFIER": 0, 
                "FILE": 0, 
                "SYNCHRONIZATION_DATA": 0, 
                "BLUETOOTH_INFORMATION": 0, 
                "EMAIL": 0, 
                "VOIP": 0, 
                "LOG": 5, 
                "IMAGE": 0, 
                "DATABASE_INFORMATION": 0, 
                "ACCOUNT_SETTINGS": 0, 
                "VIDEO": 0, 
                "PHONE_CONNECTION": 0, 
                "CALENDAR_INFORMATION": 0, 
                "WIDGET": 0, 
                "NFC": 0, 
                "LOCATION_INFORMATION": 0, 
                "BUNDLE": 0, 
                "BROWSER_INFORMATION": 0, 
                "SYSTEM_SETTINGS": 0, 
                "AUDIO": 0, 
                "PHONE_STATE": 0, 
                "IPC": 0, 
                "NOT_EXISTING": 0, 
                "ACCOUNT_INFORMATION": 0, 
                "BLUETOOTH": 0, 
                "CONTACT_INFORMATION": 0, 
                "NO_CATEGORY": 0, 
                "NETWORK_INFORMATION": 0, 
                "NETWORK": 0
            }, 
            "BROWSER_INFORMATION": {
                "SMS_MMS": 0, 
                "FILE_INFORMATION": 0, 
                "UNIQUE_IDENTIFIER": 0, 
                "FILE": 0, 
                "SYNCHRONIZATION_DATA": 0, 
                "BLUETOOTH_INFORMATION": 0, 
                "EMAIL": 0, 
                "VOIP": 0, 
                "LOG": 0, 
                "IMAGE": 0, 
                "DATABASE_INFORMATION": 0, 
                "ACCOUNT_SETTINGS": 0, 
                "VIDEO": 0, 
                "PHONE_CONNECTION": 0, 
                "CALENDAR_INFORMATION": 0, 
                "WIDGET": 0, 
                "NFC": 0, 
                "LOCATION_INFORMATION": 0, 
                "BUNDLE": 0, 
                "BROWSER_INFORMATION": 0, 
                "SYSTEM_SETTINGS": 0, 
                "AUDIO": 0, 
                "PHONE_STATE": 0, 
                "IPC": 0, 
                "NOT_EXISTING": 0, 
                "ACCOUNT_INFORMATION": 0, 
                "BLUETOOTH": 0, 
                "CONTACT_INFORMATION": 0, 
                "NO_CATEGORY": 0, 
                "NETWORK_INFORMATION": 0, 
                "NETWORK": 0
            }, 
            "SYSTEM_SETTINGS": {
                "SMS_MMS": 0, 
                "FILE_INFORMATION": 0, 
                "UNIQUE_IDENTIFIER": 0, 
                "FILE": 0, 
                "SYNCHRONIZATION_DATA": 0, 
                "BLUETOOTH_INFORMATION": 0, 
                "EMAIL": 0, 
                "VOIP": 0, 
                "LOG": 0, 
                "IMAGE": 0, 
                "DATABASE_INFORMATION": 0, 
                "ACCOUNT_SETTINGS": 0, 
                "VIDEO": 0, 
                "PHONE_CONNECTION": 0, 
                "CALENDAR_INFORMATION": 0, 
                "WIDGET": 0, 
                "NFC": 0, 
                "LOCATION_INFORMATION": 0, 
                "BUNDLE": 0, 
                "BROWSER_INFORMATION": 0, 
                "SYSTEM_SETTINGS": 0, 
                "AUDIO": 0, 
                "PHONE_STATE": 0, 
                "IPC": 0, 
                "NOT_EXISTING": 0, 
                "ACCOUNT_INFORMATION": 0, 
                "BLUETOOTH": 0, 
                "CONTACT_INFORMATION": 0, 
                "NO_CATEGORY": 0, 
                "NETWORK_INFORMATION": 0, 
                "NETWORK": 0
            }, 
            "AUDIO": {
                "SMS_MMS": 0, 
                "FILE_INFORMATION": 0, 
                "UNIQUE_IDENTIFIER": 0, 
                "FILE": 0, 
                "SYNCHRONIZATION_DATA": 0, 
                "BLUETOOTH_INFORMATION": 0, 
                "EMAIL": 0, 
                "VOIP": 0, 
                "LOG": 0, 
                "IMAGE": 0, 
                "DATABASE_INFORMATION": 0, 
                "ACCOUNT_SETTINGS": 0, 
                "VIDEO": 0, 
                "PHONE_CONNECTION": 0, 
                "CALENDAR_INFORMATION": 0, 
                "WIDGET": 0, 
                "NFC": 0, 
                "LOCATION_INFORMATION": 0, 
                "BUNDLE": 0, 
                "BROWSER_INFORMATION": 0, 
                "SYSTEM_SETTINGS": 0, 
                "AUDIO": 0, 
                "PHONE_STATE": 0, 
                "IPC": 0, 
                "NOT_EXISTING": 0, 
                "ACCOUNT_INFORMATION": 0, 
                "BLUETOOTH": 0, 
                "CONTACT_INFORMATION": 0, 
                "NO_CATEGORY": 0, 
                "NETWORK_INFORMATION": 0, 
                "NETWORK": 0
            }, 
            "PHONE_STATE": {
                "SMS_MMS": 0, 
                "FILE_INFORMATION": 0, 
                "UNIQUE_IDENTIFIER": 0, 
                "FILE": 0, 
                "SYNCHRONIZATION_DATA": 0, 
                "BLUETOOTH_INFORMATION": 0, 
                "EMAIL": 0, 
                "VOIP": 0, 
                "LOG": 0, 
                "IMAGE": 0, 
                "DATABASE_INFORMATION": 0, 
                "ACCOUNT_SETTINGS": 0, 
                "VIDEO": 0, 
                "PHONE_CONNECTION": 0, 
                "CALENDAR_INFORMATION": 0, 
                "WIDGET": 0, 
                "NFC": 0, 
                "LOCATION_INFORMATION": 0, 
                "BUNDLE": 0, 
                "BROWSER_INFORMATION": 0, 
                "SYSTEM_SETTINGS": 0, 
                "AUDIO": 0, 
                "PHONE_STATE": 0, 
                "IPC": 0, 
                "NOT_EXISTING": 0, 
                "ACCOUNT_INFORMATION": 0, 
                "BLUETOOTH": 0, 
                "CONTACT_INFORMATION": 0, 
                "NO_CATEGORY": 0, 
                "NETWORK_INFORMATION": 0, 
                "NETWORK": 0
            }, 
            "IPC": {
                "SMS_MMS": 0, 
                "FILE_INFORMATION": 0, 
                "UNIQUE_IDENTIFIER": 0, 
                "FILE": 0, 
                "SYNCHRONIZATION_DATA": 0, 
                "BLUETOOTH_INFORMATION": 0, 
                "EMAIL": 0, 
                "VOIP": 0, 
                "LOG": 0, 
                "IMAGE": 0, 
                "DATABASE_INFORMATION": 0, 
                "ACCOUNT_SETTINGS": 0, 
                "VIDEO": 0, 
                "PHONE_CONNECTION": 0, 
                "CALENDAR_INFORMATION": 0, 
                "WIDGET": 0, 
                "NFC": 0, 
                "LOCATION_INFORMATION": 0, 
                "BUNDLE": 0, 
                "BROWSER_INFORMATION": 0, 
                "SYSTEM_SETTINGS": 0, 
                "AUDIO": 0, 
                "PHONE_STATE": 0, 
                "IPC": 0, 
                "NOT_EXISTING": 0, 
                "ACCOUNT_INFORMATION": 0, 
                "BLUETOOTH": 0, 
                "CONTACT_INFORMATION": 0, 
                "NO_CATEGORY": 0, 
                "NETWORK_INFORMATION": 0, 
                "NETWORK": 0
            }, 
            "NOT_EXISTING": {
                "SMS_MMS": 0, 
                "FILE_INFORMATION": 0, 
                "UNIQUE_IDENTIFIER": 0, 
                "FILE": 0, 
                "SYNCHRONIZATION_DATA": 0, 
                "BLUETOOTH_INFORMATION": 0, 
                "EMAIL": 0, 
                "VOIP": 0, 
                "LOG": 4, 
                "IMAGE": 0, 
                "DATABASE_INFORMATION": 0, 
                "ACCOUNT_SETTINGS": 0, 
                "VIDEO": 0, 
                "PHONE_CONNECTION": 0, 
                "CALENDAR_INFORMATION": 0, 
                "WIDGET": 0, 
                "NFC": 0, 
                "LOCATION_INFORMATION": 0, 
                "BUNDLE": 0, 
                "BROWSER_INFORMATION": 0, 
                "SYSTEM_SETTINGS": 0, 
                "AUDIO": 0, 
                "PHONE_STATE": 0, 
                "IPC": 0, 
                "NOT_EXISTING": 0, 
                "ACCOUNT_INFORMATION": 0, 
                "BLUETOOTH": 0, 
                "CONTACT_INFORMATION": 0, 
                "NO_CATEGORY": 0, 
                "NETWORK_INFORMATION": 0, 
                "NETWORK": 0
            }, 
            "ACCOUNT_INFORMATION": {
                "SMS_MMS": 0, 
                "FILE_INFORMATION": 0, 
                "UNIQUE_IDENTIFIER": 0, 
                "FILE": 0, 
                "SYNCHRONIZATION_DATA": 0, 
                "BLUETOOTH_INFORMATION": 0, 
                "EMAIL": 0, 
                "VOIP": 0, 
                "LOG": 0, 
                "IMAGE": 0, 
                "DATABASE_INFORMATION": 0, 
                "ACCOUNT_SETTINGS": 0, 
                "VIDEO": 0, 
                "PHONE_CONNECTION": 0, 
                "CALENDAR_INFORMATION": 0, 
                "WIDGET": 0, 
                "NFC": 0, 
                "LOCATION_INFORMATION": 0, 
                "BUNDLE": 0, 
                "BROWSER_INFORMATION": 0, 
                "SYSTEM_SETTINGS": 0, 
                "AUDIO": 0, 
                "PHONE_STATE": 0, 
                "IPC": 0, 
                "NOT_EXISTING": 0, 
                "ACCOUNT_INFORMATION": 0, 
                "BLUETOOTH": 0, 
                "CONTACT_INFORMATION": 0, 
                "NO_CATEGORY": 0, 
                "NETWORK_INFORMATION": 0, 
                "NETWORK": 0
            }, 
            "BLUETOOTH": {
                "SMS_MMS": 0, 
                "FILE_INFORMATION": 0, 
                "UNIQUE_IDENTIFIER": 0, 
                "FILE": 0, 
                "SYNCHRONIZATION_DATA": 0, 
                "BLUETOOTH_INFORMATION": 0, 
                "EMAIL": 0, 
                "VOIP": 0, 
                "LOG": 0, 
                "IMAGE": 0, 
                "DATABASE_INFORMATION": 0, 
                "ACCOUNT_SETTINGS": 0, 
                "VIDEO": 0, 
                "PHONE_CONNECTION": 0, 
                "CALENDAR_INFORMATION": 0, 
                "WIDGET": 0, 
                "NFC": 0, 
                "LOCATION_INFORMATION": 0, 
                "BUNDLE": 0, 
                "BROWSER_INFORMATION": 0, 
                "SYSTEM_SETTINGS": 0, 
                "AUDIO": 0, 
                "PHONE_STATE": 0, 
                "IPC": 0, 
                "NOT_EXISTING": 0, 
                "ACCOUNT_INFORMATION": 0, 
                "BLUETOOTH": 0, 
                "CONTACT_INFORMATION": 0, 
                "NO_CATEGORY": 0, 
                "NETWORK_INFORMATION": 0, 
                "NETWORK": 0
            }, 
            "CONTACT_INFORMATION": {
                "SMS_MMS": 0, 
                "FILE_INFORMATION": 0, 
                "UNIQUE_IDENTIFIER": 0, 
                "FILE": 0, 
                "SYNCHRONIZATION_DATA": 0, 
                "BLUETOOTH_INFORMATION": 0, 
                "EMAIL": 0, 
                "VOIP": 0, 
                "LOG": 0, 
                "IMAGE": 0, 
                "DATABASE_INFORMATION": 0, 
                "ACCOUNT_SETTINGS": 0, 
                "VIDEO": 0, 
                "PHONE_CONNECTION": 0, 
                "CALENDAR_INFORMATION": 0, 
                "WIDGET": 0, 
                "NFC": 0, 
                "LOCATION_INFORMATION": 0, 
                "BUNDLE": 0, 
                "BROWSER_INFORMATION": 0, 
                "SYSTEM_SETTINGS": 0, 
                "AUDIO": 0, 
                "PHONE_STATE": 0, 
                "IPC": 0, 
                "NOT_EXISTING": 0, 
                "ACCOUNT_INFORMATION": 0, 
                "BLUETOOTH": 0, 
                "CONTACT_INFORMATION": 0, 
                "NO_CATEGORY": 0, 
                "NETWORK_INFORMATION": 0, 
                "NETWORK": 0
            }, 
            "NO_CATEGORY": {
                "SMS_MMS": 0, 
                "FILE_INFORMATION": 0, 
                "UNIQUE_IDENTIFIER": 0, 
                "FILE": 0, 
                "SYNCHRONIZATION_DATA": 0, 
                "BLUETOOTH_INFORMATION": 0, 
                "EMAIL": 0, 
                "VOIP": 0, 
                "LOG": 5, 
                "IMAGE": 0, 
                "DATABASE_INFORMATION": 0, 
                "ACCOUNT_SETTINGS": 0, 
                "VIDEO": 0, 
                "PHONE_CONNECTION": 0, 
                "CALENDAR_INFORMATION": 0, 
                "WIDGET": 0, 
                "NFC": 0, 
                "LOCATION_INFORMATION": 0, 
                "BUNDLE": 0, 
                "BROWSER_INFORMATION": 0, 
                "SYSTEM_SETTINGS": 0, 
                "AUDIO": 0, 
                "PHONE_STATE": 0, 
                "IPC": 0, 
                "NOT_EXISTING": 0, 
                "ACCOUNT_INFORMATION": 0, 
                "BLUETOOTH": 0, 
                "CONTACT_INFORMATION": 0, 
                "NO_CATEGORY": 0, 
                "NETWORK_INFORMATION": 0, 
                "NETWORK": 0
            }, 
            "NETWORK_INFORMATION": {
                "SMS_MMS": 0, 
                "FILE_INFORMATION": 0, 
                "UNIQUE_IDENTIFIER": 0, 
                "FILE": 0, 
                "SYNCHRONIZATION_DATA": 0, 
                "BLUETOOTH_INFORMATION": 0, 
                "EMAIL": 0, 
                "VOIP": 0, 
                "LOG": 0, 
                "IMAGE": 0, 
                "DATABASE_INFORMATION": 0, 
                "ACCOUNT_SETTINGS": 0, 
                "VIDEO": 0, 
                "PHONE_CONNECTION": 0, 
                "CALENDAR_INFORMATION": 0, 
                "WIDGET": 0, 
                "NFC": 0, 
                "LOCATION_INFORMATION": 0, 
                "BUNDLE": 0, 
                "BROWSER_INFORMATION": 0, 
                "SYSTEM_SETTINGS": 0, 
                "AUDIO": 0, 
                "PHONE_STATE": 0, 
                "IPC": 0, 
                "NOT_EXISTING": 0, 
                "ACCOUNT_INFORMATION": 0, 
                "BLUETOOTH": 0, 
                "CONTACT_INFORMATION": 0, 
                "NO_CATEGORY": 0, 
                "NETWORK_INFORMATION": 0, 
                "NETWORK": 0
            }, 
            "NETWORK": {
                "SMS_MMS": 0, 
                "FILE_INFORMATION": 0, 
                "UNIQUE_IDENTIFIER": 0, 
                "FILE": 0, 
                "SYNCHRONIZATION_DATA": 0, 
                "BLUETOOTH_INFORMATION": 0, 
                "EMAIL": 0, 
                "VOIP": 0, 
                "LOG": 0, 
                "IMAGE": 0, 
                "DATABASE_INFORMATION": 0, 
                "ACCOUNT_SETTINGS": 0, 
                "VIDEO": 0, 
                "PHONE_CONNECTION": 0, 
                "CALENDAR_INFORMATION": 0, 
                "WIDGET": 0, 
                "NFC": 0, 
                "LOCATION_INFORMATION": 0, 
                "BUNDLE": 0, 
                "BROWSER_INFORMATION": 0, 
                "SYSTEM_SETTINGS": 0, 
                "AUDIO": 0, 
                "PHONE_STATE": 0, 
                "IPC": 0, 
                "NOT_EXISTING": 0, 
                "ACCOUNT_INFORMATION": 0, 
                "BLUETOOTH": 0, 
                "CONTACT_INFORMATION": 0, 
                "NO_CATEGORY": 0, 
                "NETWORK_INFORMATION": 0, 
                "NETWORK": 0
            }
        }
    }, 
    "Dynamic_analysis": {
        "Droidbox": {
            "apkName": "/apks/samples//BW/8c2cee6a57b93201ce76e760a795e10ce3850cb1cdee19ea51c5cc9efa56d871.apk", 
            "enfperm": [], 
            "recvnet": {}, 
            "cryptousage": {}, 
            "recvsaction": {}, 
            "servicestart": {}, 
            "sendnet": {}, 
            "sendsms": {}, 
            "accessedfiles": {
                "1596692996": "/dev/input/event0", 
                "1315575413": "/data/data/com.android.gallery3d/shared_prefs/com.android.gallery3d_preferences.xml", 
                "211778281": "/data/data/com.android.providers.contacts/shared_prefs/com.android.providers.contacts_preferences.xml", 
                "424847973": "/data/data/com.android.gallery3d/shared_prefs/com.android.gallery3d_preferences.xml", 
                "1856265807": "/proc/223/net/xt_qtaguid/iface_stat_all", 
                "1294892606": "/proc/223/net/xt_qtaguid/iface_stat_all", 
                "458172155": "/data/data/com.android.gallery3d/shared_prefs/com.android.gallery3d_preferences.xml"
            }, 
            "fdaccess": {
                "2.7806079387664795": {
                    "path": "/data/data/com.android.gallery3d/shared_prefs/com.android.gallery3d_preferences.xml", 
                    "operation": "write", 
                    "data": "3c3f786d6c2076657273696f6e3d27312e302720656e636f64696e673d277574662d3827207374616e64616c6f6e653d2779657327203f3e0a3c6d61703e0a3c696e74206e616d653d227061636b616765732d76657273696f6e222076616c75653d2235", 
                    "id": "458172155", 
                    "type": "file write"
                }, 
                "2.950007915496826": {
                    "path": "/data/data/com.android.gallery3d/shared_prefs/com.android.gallery3d_preferences.xml", 
                    "operation": "write", 
                    "data": "3c3f786d6c2076657273696f6e3d27312e302720656e636f64696e673d277574662d3827207374616e64616c6f6e653d2779657327203f3e0a3c6d61703e0a3c696e74206e616d653d227061636b616765732d76657273696f6e222076616c75653d2237", 
                    "id": "1315575413", 
                    "type": "file write"
                }, 
                "63.74388909339905": {
                    "path": "/proc/223/net/xt_qtaguid/iface_stat_all", 
                    "operation": "read", 
                    "data": "6c6f20312030203020302030203231323420333120323132342033310a657468302031203020302030203020313231383733203130333820313336353631203937320a000000000000000000000000000000000000000000000000000000000000000000", 
                    "id": "1856265807", 
                    "type": "file read"
                }, 
                "63.75279092788696": {
                    "path": "/proc/223/net/xt_qtaguid/iface_stat_all", 
                    "operation": "read", 
                    "data": "3937320a3631203937320a203937320a3631203937320a320a320a320a320a320a203937320a37320a203937320a37320a203937320a320a320a320a320a320a37320a000000000000000000000000000000000000000000000000000000000000000000", 
                    "id": "1294892606", 
                    "type": "file read"
                }, 
                "4.111238956451416": {
                    "path": "/data/data/com.android.providers.contacts/shared_prefs/com.android.providers.contacts_preferences.xml", 
                    "operation": "write", 
                    "data": "3c3f786d6c2076657273696f6e3d27312e302720656e636f64696e673d277574662d3827207374616e64616c6f6e653d2779657327203f3e0a3c6d61703e0a3c737472696e67206e616d653d226c6f63616c65223e656e5f55533c2f737472696e673e0a", 
                    "id": "211778281", 
                    "type": "file write"
                }, 
                "0.0008029937744140625": {
                    "path": "/dev/input/event0", 
                    "operation": "write", 
                    "data": "efbfbd060000efbfbdefbfbd0c000500000000000000", 
                    "id": "1596692996", 
                    "type": "file write"
                }, 
                "2.889984130859375": {
                    "path": "/data/data/com.android.gallery3d/shared_prefs/com.android.gallery3d_preferences.xml", 
                    "operation": "write", 
                    "data": "3c3f786d6c2076657273696f6e3d27312e302720656e636f64696e673d277574662d3827207374616e64616c6f6e653d2779657327203f3e0a3c6d61703e0a3c696e74206e616d653d227061636b616765732d76657273696f6e222076616c75653d2236", 
                    "id": "424847973", 
                    "type": "file write"
                }
            }, 
            "dataleaks": {}, 
            "opennet": {}, 
            "dexclass": {
                "0.02319812774658203": {
                    "path": "/data/app/com.touringplans.lines.android-1.apk", 
                    "type": "dexload"
                }
            }, 
            "hashes": [
                "6bb83f167d1369b525f60b73d5162083", 
                "31d815fc760f5b5db9c3bde7cb0df1638d7ea7bf", 
                "8c2cee6a57b93201ce76e760a795e10ce3850cb1cdee19ea51c5cc9efa56d871"
            ], 
            "closenet": {}, 
            "phonecalls": {}
        }, 
        "Strace": "/apks/Dynamic/Strace/8c2cee6a57b93201ce76e760a795e10ce3850cb1cdee19ea51c5cc9efa56d871.csv"
    }, 
    "VirusTotal": {
        "scan_id": "8c2cee6a57b93201ce76e760a795e10ce3850cb1cdee19ea51c5cc9efa56d871-1668323731", 
        "sha1": "31d815fc760f5b5db9c3bde7cb0df1638d7ea7bf", 
        "resource": "8c2cee6a57b93201ce76e760a795e10ce3850cb1cdee19ea51c5cc9efa56d871", 
        "response_code": 1, 
        "scan_date": "2022-11-13 07:15:31", 
        "permalink": "https://www.virustotal.com/gui/file/8c2cee6a57b93201ce76e760a795e10ce3850cb1cdee19ea51c5cc9efa56d871/detection/f-8c2cee6a57b93201ce76e760a795e10ce3850cb1cdee19ea51c5cc9efa56d871-1668323731", 
        "verbose_msg": "Scan finished, information embedded", 
        "sha256": "8c2cee6a57b93201ce76e760a795e10ce3850cb1cdee19ea51c5cc9efa56d871", 
        "positives": 0, 
        "total": 66, 
        "md5": "6bb83f167d1369b525f60b73d5162083", 
        "scans": {
            "Bkav": {
                "detected": false, 
                "version": "1.3.0.9899", 
                "result": null, 
                "update": "20221113"
            }, 
            "Lionic": {
                "detected": false, 
                "version": "7.5", 
                "result": null, 
                "update": "20221113"
            }, 
            "MicroWorld-eScan": {
                "detected": false, 
                "version": "14.0.409.0", 
                "result": null, 
                "update": "20221113"
            }, 
            "FireEye": {
                "detected": false, 
                "version": "35.24.1.0", 
                "result": null, 
                "update": "20221113"
            }, 
            "CAT-QuickHeal": {
                "detected": false, 
                "version": "22.00", 
                "result": null, 
                "update": "20221112"
            }, 
            "McAfee": {
                "detected": false, 
                "version": "6.0.6.653", 
                "result": null, 
                "update": "20221023"
            }, 
            "Malwarebytes": {
                "detected": false, 
                "version": "4.3.3.37", 
                "result": null, 
                "update": "20221113"
            }, 
            "VIPRE": {
                "detected": false, 
                "version": "6.0.0.35", 
                "result": null, 
                "update": "20221112"
            }, 
            "Sangfor": {
                "detected": false, 
                "version": "2.23.0.0", 
                "result": null, 
                "update": "20221110"
            }, 
            "Trustlook": {
                "detected": false, 
                "version": "1.0", 
                "result": null, 
                "update": "20221113"
            }, 
            "BitDefender": {
                "detected": false, 
                "version": "7.2", 
                "result": null, 
                "update": "20221113"
            }, 
            "K7GW": {
                "detected": false, 
                "version": "12.49.45282", 
                "result": null, 
                "update": "20221111"
            }, 
            "K7AntiVirus": {
                "detected": false, 
                "version": "12.49.45300", 
                "result": null, 
                "update": "20221113"
            }, 
            "BitDefenderTheta": {
                "detected": false, 
                "version": "7.2.37796.0", 
                "result": null, 
                "update": "20221109"
            }, 
            "VirIT": {
                "detected": false, 
                "version": "9.5.323", 
                "result": null, 
                "update": "20221111"
            }, 
            "Cyren": {
                "detected": false, 
                "version": "6.5.1.2", 
                "result": null, 
                "update": "20221113"
            }, 
            "SymantecMobileInsight": {
                "detected": false, 
                "version": "2.0", 
                "result": null, 
                "update": "20220208"
            }, 
            "Symantec": {
                "detected": false, 
                "version": "1.19.0.0", 
                "result": null, 
                "update": "20221112"
            }, 
            "ESET-NOD32": {
                "detected": false, 
                "version": "26246", 
                "result": null, 
                "update": "20221112"
            }, 
            "Baidu": {
                "detected": false, 
                "version": "1.0.0.2", 
                "result": null, 
                "update": "20190318"
            }, 
            "TrendMicro-HouseCall": {
                "detected": false, 
                "version": "10.0.0.1040", 
                "result": null, 
                "update": "20221113"
            }, 
            "Avast": {
                "detected": false, 
                "version": "22.11.7701.0", 
                "result": null, 
                "update": "20221113"
            }, 
            "ClamAV": {
                "detected": false, 
                "version": "0.105.1.0", 
                "result": null, 
                "update": "20221112"
            }, 
            "Kaspersky": {
                "detected": false, 
                "version": "21.0.1.45", 
                "result": null, 
                "update": "20221113"
            }, 
            "Alibaba": {
                "detected": false, 
                "version": "0.3.0.5", 
                "result": null, 
                "update": "20190527"
            }, 
            "NANO-Antivirus": {
                "detected": false, 
                "version": "1.0.146.25648", 
                "result": null, 
                "update": "20221113"
            }, 
            "Cynet": {
                "detected": false, 
                "version": "4.0.0.27", 
                "result": null, 
                "update": "20221113"
            }, 
            "ViRobot": {
                "detected": false, 
                "version": "2014.3.20.0", 
                "result": null, 
                "update": "20221112"
            }, 
            "Tencent": {
                "detected": false, 
                "version": "1.0.0.1", 
                "result": null, 
                "update": "20221113"
            }, 
            "Ad-Aware": {
                "detected": false, 
                "version": "3.0.21.193", 
                "result": null, 
                "update": "20221113"
            }, 
            "Emsisoft": {
                "detected": false, 
                "version": "2022.6.0.32461", 
                "result": null, 
                "update": "20221113"
            }, 
            "Comodo": {
                "detected": false, 
                "version": "35150", 
                "result": null, 
                "update": "20221112"
            }, 
            "F-Secure": {
                "detected": false, 
                "version": "18.10.1137.128", 
                "result": null, 
                "update": "20221113"
            }, 
            "DrWeb": {
                "detected": false, 
                "version": "7.0.58.8230", 
                "result": null, 
                "update": "20221113"
            }, 
            "Zillya": {
                "detected": false, 
                "version": "2.0.0.4750", 
                "result": null, 
                "update": "20221111"
            }, 
            "TrendMicro": {
                "detected": false, 
                "version": "11.0.0.1006", 
                "result": null, 
                "update": "20221113"
            }, 
            "McAfee-GW-Edition": {
                "detected": false, 
                "version": "v2019.1.2+3728", 
                "result": null, 
                "update": "20221113"
            }, 
            "CMC": {
                "detected": false, 
                "version": "2.4.2022.1", 
                "result": null, 
                "update": "20221111"
            }, 
            "Sophos": {
                "detected": false, 
                "version": "1.4.1.0", 
                "result": null, 
                "update": "20221113"
            }, 
            "Ikarus": {
                "detected": false, 
                "version": "6.0.31.0", 
                "result": null, 
                "update": "20221112"
            }, 
            "GData": {
                "detected": false, 
                "version": "A:25.34487B:27.29521", 
                "result": null, 
                "update": "20221113"
            }, 
            "Jiangmin": {
                "detected": false, 
                "version": "16.0.100", 
                "result": null, 
                "update": "20221113"
            }, 
            "Avira": {
                "detected": false, 
                "version": "8.3.3.16", 
                "result": null, 
                "update": "20221113"
            }, 
            "Antiy-AVL": {
                "detected": false, 
                "version": "3.0", 
                "result": null, 
                "update": "20221113"
            }, 
            "Kingsoft": {
                "detected": false, 
                "version": "2017.9.26.565", 
                "result": null, 
                "update": "20221113"
            }, 
            "Microsoft": {
                "detected": false, 
                "version": "1.1.19800.4", 
                "result": null, 
                "update": "20221113"
            }, 
            "Gridinsoft": {
                "detected": false, 
                "version": "1.0.100.174", 
                "result": null, 
                "update": "20221113"
            }, 
            "Arcabit": {
                "detected": false, 
                "version": "2022.0.0.18", 
                "result": null, 
                "update": "20221112"
            }, 
            "SUPERAntiSpyware": {
                "detected": false, 
                "version": "5.6.0.1032", 
                "result": null, 
                "update": "20221112"
            }, 
            "ZoneAlarm": {
                "detected": false, 
                "version": "1.0", 
                "result": null, 
                "update": "20221113"
            }, 
            "Avast-Mobile": {
                "detected": false, 
                "version": "221112-00", 
                "result": null, 
                "update": "20221112"
            }, 
            "Google": {
                "detected": false, 
                "version": "1668315656", 
                "result": null, 
                "update": "20221113"
            }, 
            "BitDefenderFalx": {
                "detected": false, 
                "version": "2.0.936", 
                "result": null, 
                "update": "20220103"
            }, 
            "AhnLab-V3": {
                "detected": false, 
                "version": "3.22.2.10299", 
                "result": null, 
                "update": "20221113"
            }, 
            "Acronis": {
                "detected": false, 
                "version": "1.2.0.112", 
                "result": null, 
                "update": "20221105"
            }, 
            "VBA32": {
                "detected": false, 
                "version": "5.0.0", 
                "result": null, 
                "update": "20221111"
            }, 
            "ALYac": {
                "detected": false, 
                "version": "1.1.3.1", 
                "result": null, 
                "update": "20221113"
            }, 
            "TACHYON": {
                "detected": false, 
                "version": "2022-11-13.02", 
                "result": null, 
                "update": "20221113"
            }, 
            "Zoner": {
                "detected": false, 
                "version": "2.2.2.0", 
                "result": null, 
                "update": "20221112"
            }, 
            "Rising": {
                "detected": false, 
                "version": "25.0.0.27", 
                "result": null, 
                "update": "20221113"
            }, 
            "Yandex": {
                "detected": false, 
                "version": "5.5.2.24", 
                "result": null, 
                "update": "20221112"
            }, 
            "MAX": {
                "detected": false, 
                "version": "2019.9.16.1", 
                "result": null, 
                "update": "20221113"
            }, 
            "MaxSecure": {
                "detected": false, 
                "version": "1.0.0.1", 
                "result": null, 
                "update": "20221112"
            }, 
            "Fortinet": {
                "detected": false, 
                "version": "6.4.258.0", 
                "result": null, 
                "update": "20221113"
            }, 
            "AVG": {
                "detected": false, 
                "version": "22.11.7701.0", 
                "result": null, 
                "update": "20221113"
            }, 
            "Panda": {
                "detected": false, 
                "version": "4.6.4.2", 
                "result": null, 
                "update": "20221112"
            }
        }
    }
}